liquid/__init__.py
liquid/aqua_application_scopes.py
liquid/aqua_authentication.py
liquid/aqua_cwp.py
liquid/aqua_incidents.py
liquid/aqua_user_management.py
liquid_sdk-0.0.2.dist-info/LICENSE
liquid_sdk-0.0.2.dist-info/METADATA
liquid_sdk-0.0.2.dist-info/WHEEL
liquid_sdk-0.0.2.dist-info/top_level.txt
liquid_sdk-0.0.2.dist-info/RECORD
