Metadata-Version: 2.1
Name: liquid-sdk
Version: 0.0.2
Author-email: Richard Julian <richard@thatcloudgroup.com>, Jeremiah Owen <jeremiah@thatcloudgroup.com>
License: Apache License 2.0
Project-URL: Homepage, https://github.com/That-Cloud-Group/liquid
Project-URL: Documentation, https://github.com/That-Cloud-Group/liquid
Project-URL: Repository, https://github.com/That-Cloud-Group/liquid
Project-URL: Bug Tracker, https://github.com/That-Cloud-Group/liquid
Project-URL: Changelog, https://github.com/That-Cloud-Group/liquid
Keywords: security,tooling,kubernetes,cloud
Classifier: Programming Language :: Python
Requires-Python: >=3.8
License-File: LICENSE
Requires-Dist: requests
Requires-Dist: PyJWT
